{
  "rows": [
    {
      "cid": "C001",
      "name": "TES_Ta_Absorber_Stack_side_entry",
      "category": "detector",
      "material": "Ta",
      "shape": "x_disc_stack",
      "volume_cm3": 15.227999999999998,
      "mass_kg": 0.25415531999999996
    },
    {
      "cid": "C002",
      "name": "Si_Substrate_Stack_side_entry",
      "category": "substrate",
      "material": "Silicon",
      "shape": "x_disc_stack",
      "volume_cm3": 2.7369555198074282,
      "mass_kg": 0.0063743694056315
    },
    {
      "cid": "C003",
      "name": "Cu_SubstrateSupport_OpenRing_L1",
      "category": "thermal_link",
      "material": "Copper",
      "shape": "x_annulus",
      "volume_cm3": 1.3359622759390597,
      "mass_kg": 0.011970221992413975
    },
    {
      "cid": "C004",
      "name": "Cu_SubstrateSupport_OpenRing_L2",
      "category": "thermal_link",
      "material": "Copper",
      "shape": "x_annulus",
      "volume_cm3": 1.3359622759390597,
      "mass_kg": 0.011970221992413975
    },
    {
      "cid": "C005",
      "name": "Cu_SubstrateSupport_OpenRing_L3",
      "category": "thermal_link",
      "material": "Copper",
      "shape": "x_annulus",
      "volume_cm3": 1.3359622759390597,
      "mass_kg": 0.011970221992413975
    },
    {
      "cid": "C006",
      "name": "Cu_SubstrateSupport_OpenRing_L4",
      "category": "thermal_link",
      "material": "Copper",
      "shape": "x_annulus",
      "volume_cm3": 1.3359622759390597,
      "mass_kg": 0.011970221992413975
    },
    {
      "cid": "C007",
      "name": "Cu_SubstrateSupport_OpenRing_L5",
      "category": "thermal_link",
      "material": "Copper",
      "shape": "x_annulus",
      "volume_cm3": 1.3359622759390597,
      "mass_kg": 0.011970221992413975
    },
    {
      "cid": "C008",
      "name": "Cu_SubstrateSupport_SolidDisk_L0_deepest",
      "category": "thermal_link",
      "material": "Copper",
      "shape": "x_disc",
      "volume_cm3": 5.32185795518111,
      "mass_kg": 0.047683847278422745
    },
    {
      "cid": "C009",
      "name": "Cu_SubstrateSupport_EdgeRod_1",
      "category": "thermal_link",
      "material": "Copper",
      "shape": "x_cylinder_offaxis",
      "volume_cm3": 0.2057743188101315,
      "mass_kg": 0.0018437378965387786
    },
    {
      "cid": "C010",
      "name": "Cu_SubstrateSupport_EdgeRod_2",
      "category": "thermal_link",
      "material": "Copper",
      "shape": "x_cylinder_offaxis",
      "volume_cm3": 0.2057743188101315,
      "mass_kg": 0.0018437378965387786
    },
    {
      "cid": "C011",
      "name": "Cu_SubstrateSupport_EdgeRod_3",
      "category": "thermal_link",
      "material": "Copper",
      "shape": "x_cylinder_offaxis",
      "volume_cm3": 0.2057743188101315,
      "mass_kg": 0.0018437378965387786
    },
    {
      "cid": "C012",
      "name": "Cu_SubstrateSupport_EdgeRod_4",
      "category": "thermal_link",
      "material": "Copper",
      "shape": "x_cylinder_offaxis",
      "volume_cm3": 0.2057743188101315,
      "mass_kg": 0.0018437378965387786
    },
    {
      "cid": "C013",
      "name": "Cu_ColdFinger_OffAxis_YP_ZP_from_Disk_to_Stem",
      "category": "thermal_link",
      "material": "Copper",
      "shape": "x_cylinder_offaxis",
      "volume_cm3": 0.21151715018089362,
      "mass_kg": 0.001895193665620807
    },
    {
      "cid": "C014",
      "name": "Cu_ColdFinger_OffAxis_YM_ZP_from_Disk_to_Stem",
      "category": "thermal_link",
      "material": "Copper",
      "shape": "x_cylinder_offaxis",
      "volume_cm3": 0.21151715018089362,
      "mass_kg": 0.001895193665620807
    },
    {
      "cid": "C015",
      "name": "Cu_ColdFinger_OffAxis_YP_ZM_from_Disk_to_Stem",
      "category": "thermal_link",
      "material": "Copper",
      "shape": "x_cylinder_offaxis",
      "volume_cm3": 0.27585696772641255,
      "mass_kg": 0.0024716784308286568
    },
    {
      "cid": "C016",
      "name": "Cu_ColdFinger_OffAxis_YM_ZM_from_Disk_to_Stem",
      "category": "thermal_link",
      "material": "Copper",
      "shape": "x_cylinder_offaxis",
      "volume_cm3": 0.27585696772641255,
      "mass_kg": 0.0024716784308286568
    },
    {
      "cid": "C017",
      "name": "Cu_ColdFinger_Stem_YP_ZP_to_MXC",
      "category": "thermal_link",
      "material": "Copper",
      "shape": "z_cylinder_offaxis",
      "volume_cm3": 0.3056141333412151,
      "mass_kg": 0.0027383026347372877
    },
    {
      "cid": "C018",
      "name": "Cu_ColdFinger_Stem_YM_ZP_to_MXC",
      "category": "thermal_link",
      "material": "Copper",
      "shape": "z_cylinder_offaxis",
      "volume_cm3": 0.3056141333412151,
      "mass_kg": 0.0027383026347372877
    },
    {
      "cid": "C019",
      "name": "Cu_ColdFinger_Stem_YP_ZM_to_MXC",
      "category": "thermal_link",
      "material": "Copper",
      "shape": "z_cylinder_offaxis",
      "volume_cm3": 0.4825486315913924,
      "mass_kg": 0.004323635739058876
    },
    {
      "cid": "C020",
      "name": "Cu_ColdFinger_Stem_YM_ZM_to_MXC",
      "category": "thermal_link",
      "material": "Copper",
      "shape": "z_cylinder_offaxis",
      "volume_cm3": 0.4825486315913924,
      "mass_kg": 0.004323635739058876
    },
    {
      "cid": "C021",
      "name": "Cu_MXC_Clamp_Pad_YP_ZP_for_OffAxisStem",
      "category": "thermal_link",
      "material": "Copper",
      "shape": "z_cylinder_offaxis",
      "volume_cm3": 0.07696902001294993,
      "mass_kg": 0.0006896424193160314
    },
    {
      "cid": "C022",
      "name": "Cu_MXC_Clamp_Pad_YM_ZP_for_OffAxisStem",
      "category": "thermal_link",
      "material": "Copper",
      "shape": "z_cylinder_offaxis",
      "volume_cm3": 0.07696902001294993,
      "mass_kg": 0.0006896424193160314
    },
    {
      "cid": "C023",
      "name": "Cu_MXC_Clamp_Pad_YP_ZM_for_OffAxisStem",
      "category": "thermal_link",
      "material": "Copper",
      "shape": "z_cylinder_offaxis",
      "volume_cm3": 0.07696902001294993,
      "mass_kg": 0.0006896424193160314
    },
    {
      "cid": "C024",
      "name": "Cu_MXC_Clamp_Pad_YM_ZM_for_OffAxisStem",
      "category": "thermal_link",
      "material": "Copper",
      "shape": "z_cylinder_offaxis",
      "volume_cm3": 0.07696902001294993,
      "mass_kg": 0.0006896424193160314
    },
    {
      "cid": "C025",
      "name": "Nb_SideEntry_Sample_Can_with_side_aperture",
      "category": "magnetic_sample_can",
      "material": "Nb",
      "shape": "x_can",
      "volume_cm3": 19.729594563625596,
      "mass_kg": 0.16908262541027136
    },
    {
      "cid": "C026",
      "name": "Cryoperm_Horizontal_Sleeve_1p2mm",
      "category": "magnetic_shield",
      "material": "Cryoperm",
      "shape": "x_can",
      "volume_cm3": 53.910974006291724,
      "mass_kg": 0.469025473854738
    },
    {
      "cid": "C027",
      "name": "Al_50mK_Local_Can_side_entry",
      "category": "cryostat_shell",
      "material": "Aluminium",
      "shape": "x_can",
      "volume_cm3": 40.624135665499516,
      "mass_kg": 0.10968516629684871
    },
    {
      "cid": "C028",
      "name": "ColdPlate_MXC_50mK_SD_anchor",
      "category": "cold_plate",
      "material": "Copper",
      "shape": "z_cylinder",
      "volume_cm3": 103.22016822634625,
      "mass_kg": 0.9248527073080625
    },
    {
      "cid": "C029",
      "name": "ColdPlate_CP_100mK_intercept",
      "category": "cold_plate",
      "material": "Copper",
      "shape": "z_cylinder",
      "volume_cm3": 95.56724852220151,
      "mass_kg": 0.8562825467589256
    },
    {
      "cid": "C030",
      "name": "ColdPlate_Still_0p7K",
      "category": "cold_plate",
      "material": "Copper",
      "shape": "z_cylinder",
      "volume_cm3": 145.97096105639616,
      "mass_kg": 1.3078998110653097
    },
    {
      "cid": "C031",
      "name": "ColdPlate_4K",
      "category": "cold_plate",
      "material": "Copper",
      "shape": "z_cylinder",
      "volume_cm3": 203.8767968473632,
      "mass_kg": 1.8267360997523745
    },
    {
      "cid": "C032",
      "name": "ColdPlate_60K",
      "category": "cold_plate",
      "material": "Aluminium",
      "shape": "z_cylinder",
      "volume_cm3": 311.4166549723954,
      "mass_kg": 0.8408249684254676
    },
    {
      "cid": "C033",
      "name": "Plate_300K_Top_Service_Lid",
      "category": "vacuum_jacket",
      "material": "Aluminium",
      "shape": "z_cylinder",
      "volume_cm3": 598.2849049496402,
      "mass_kg": 1.6153692433640288
    },
    {
      "cid": "C034",
      "name": "Still_Shield_Al_side_window",
      "category": "cryostat_shell",
      "material": "Aluminium",
      "shape": "z_can_open_top",
      "volume_cm3": 136.58702380012303,
      "mass_kg": 0.36878496426033225
    },
    {
      "cid": "C035",
      "name": "Shield_4K_Al_side_window",
      "category": "cryostat_shell",
      "material": "Aluminium",
      "shape": "z_can_open_top",
      "volume_cm3": 271.4005808481822,
      "mass_kg": 0.732781568290092
    },
    {
      "cid": "C036",
      "name": "Shield_60K_Al_side_window",
      "category": "cryostat_shell",
      "material": "Aluminium",
      "shape": "z_can_open_top",
      "volume_cm3": 506.81743484037275,
      "mass_kg": 1.3684070740690064
    },
    {
      "cid": "C037",
      "name": "Vacuum_Jacket_Al_266mmClass_side_port",
      "category": "vacuum_jacket",
      "material": "Aluminium",
      "shape": "z_can_open_top",
      "volume_cm3": 1960.268992838387,
      "mass_kg": 5.292726280663645
    },
    {
      "cid": "C038",
      "name": "Win_50mK_Al_foil_side",
      "category": "window",
      "material": "Aluminium",
      "shape": "x_disc",
      "volume_cm3": 0.028293214854156208,
      "mass_kg": 7.639168010622177e-05
    },
    {
      "cid": "C039",
      "name": "Win_Still_Al_foil_side",
      "category": "window",
      "material": "Aluminium",
      "shape": "x_disc",
      "volume_cm3": 0.028293214854156208,
      "mass_kg": 7.639168010622177e-05
    },
    {
      "cid": "C040",
      "name": "Win_4K_Al_foil_side",
      "category": "window",
      "material": "Aluminium",
      "shape": "x_disc",
      "volume_cm3": 0.028293214854156208,
      "mass_kg": 7.639168010622177e-05
    },
    {
      "cid": "C041",
      "name": "Win_60K_Al_foil_side",
      "category": "window",
      "material": "Aluminium",
      "shape": "x_disc",
      "volume_cm3": 0.028293214854156208,
      "mass_kg": 7.639168010622177e-05
    },
    {
      "cid": "C042",
      "name": "Win_Be_Vacuum_150um_side",
      "category": "window",
      "material": "Be",
      "shape": "x_disc",
      "volume_cm3": 0.16975928912493723,
      "mass_kg": 0.00031405468488113393
    },
    {
      "cid": "C043",
      "name": "Win_Outer_Al_Filter_side",
      "category": "window",
      "material": "Aluminium",
      "shape": "x_disc",
      "volume_cm3": 0.03395185782498745,
      "mass_kg": 9.167001612746611e-05
    },
    {
      "cid": "C044",
      "name": "DR_MixingChamber_Cu",
      "category": "dr_unit",
      "material": "Copper",
      "shape": "z_cylinder",
      "volume_cm3": 27.369555198074284,
      "mass_kg": 0.24523121457474562
    },
    {
      "cid": "C045",
      "name": "DR_MXC_Sinter_HEX_AgProxy",
      "category": "dr_unit",
      "material": "SilverSinterProxy",
      "shape": "z_annulus",
      "volume_cm3": 33.929200658769766,
      "mass_kg": 0.16964600329384882
    },
    {
      "cid": "C046",
      "name": "DR_Continuous_HEX_CuNi_MXC_to_CP",
      "category": "dr_unit",
      "material": "CuNi",
      "shape": "z_annulus_phi",
      "volume_cm3": 12.706485646709266,
      "mass_kg": 0.11308772225571248
    },
    {
      "cid": "C047",
      "name": "DR_Continuous_HEX_CuNi_CP_to_Still",
      "category": "dr_unit",
      "material": "CuNi",
      "shape": "z_annulus_phi",
      "volume_cm3": 12.706485646709266,
      "mass_kg": 0.11308772225571248
    },
    {
      "cid": "C048",
      "name": "DR_Still_Pot_Cu",
      "category": "dr_unit",
      "material": "Copper",
      "shape": "z_cylinder",
      "volume_cm3": 33.979466141227206,
      "mass_kg": 0.30445601662539584
    },
    {
      "cid": "C049",
      "name": "DR_Still_Heater_SS_ring",
      "category": "dr_unit",
      "material": "StainlessSteel",
      "shape": "z_annulus",
      "volume_cm3": 1.0555751316061697,
      "mass_kg": 0.008444601052849358
    },
    {
      "cid": "C050",
      "name": "DR_4K_Condenser_Cu",
      "category": "dr_unit",
      "material": "Copper",
      "shape": "z_cylinder",
      "volume_cm3": 12.214512237157116,
      "mass_kg": 0.10944202964492777
    },
    {
      "cid": "C051",
      "name": "DR_60K_Charcoal_Trap",
      "category": "dr_unit",
      "material": "CharcoalProxy",
      "shape": "z_cylinder",
      "volume_cm3": 24.950528854810138,
      "mass_kg": 0.029940634625772164
    },
    {
      "cid": "C052",
      "name": "DR_Capillary_CuNi_MXC_CP",
      "category": "service_proxy",
      "material": "CuNi",
      "shape": "z_annulus_phi",
      "volume_cm3": 2.3788441165876675,
      "mass_kg": 0.021171712637630243
    },
    {
      "cid": "C053",
      "name": "DR_Capillary_CuNi_CP_Still",
      "category": "service_proxy",
      "material": "CuNi",
      "shape": "z_annulus_phi",
      "volume_cm3": 2.3788441165876675,
      "mass_kg": 0.021171712637630243
    },
    {
      "cid": "C054",
      "name": "DR_Capillary_CuNi_Still_4K",
      "category": "service_proxy",
      "material": "CuNi",
      "shape": "z_annulus_phi",
      "volume_cm3": 6.870165505124617,
      "mass_kg": 0.061144472995609093
    },
    {
      "cid": "C055",
      "name": "DR_Capillary_CuNi_4K_60K",
      "category": "service_proxy",
      "material": "CuNi",
      "shape": "z_annulus_phi",
      "volume_cm3": 7.885689100308699,
      "mass_kg": 0.07018263299274743
    },
    {
      "cid": "C056",
      "name": "DR_Still_PumpLine_SS_to_300K_top",
      "category": "service_proxy",
      "material": "StainlessSteel",
      "shape": "box",
      "volume_cm3": 4.064000000000001,
      "mass_kg": 0.032512000000000006
    },
    {
      "cid": "C057",
      "name": "PreCool_FlexLink_Cu_remote_interface",
      "category": "service_proxy",
      "material": "Copper",
      "shape": "box",
      "volume_cm3": 1.3499999999999999,
      "mass_kg": 0.012096
    },
    {
      "cid": "C058",
      "name": "SQUID_uMUX_Box_Al_relocated_offbeam_minimal",
      "category": "service_proxy",
      "material": "Aluminium",
      "shape": "box",
      "volume_cm3": 2.304,
      "mass_kg": 0.006220799999999999
    },
    {
      "cid": "C059",
      "name": "NbTi_Bundle_bay_to_MXC",
      "category": "service_proxy",
      "material": "NbTiCableProxy",
      "shape": "z_annulus_phi",
      "volume_cm3": 16.438697719173998,
      "mass_kg": 0.10685153517463099
    },
    {
      "cid": "C060",
      "name": "NbTi_Bundle_MXC_CP",
      "category": "service_proxy",
      "material": "NbTiCableProxy",
      "shape": "z_annulus_phi",
      "volume_cm3": 9.08454347638563,
      "mass_kg": 0.059049532596506596
    },
    {
      "cid": "C061",
      "name": "NbTi_Bundle_CP_Still",
      "category": "service_proxy",
      "material": "NbTiCableProxy",
      "shape": "z_annulus_phi",
      "volume_cm3": 9.08454347638563,
      "mass_kg": 0.059049532596506596
    },
    {
      "cid": "C062",
      "name": "NbTi_Bundle_Still_4K",
      "category": "service_proxy",
      "material": "NbTiCableProxy",
      "shape": "z_annulus_phi",
      "volume_cm3": 24.56832269257447,
      "mass_kg": 0.15969409750173405
    },
    {
      "cid": "C063",
      "name": "NbTi_Bundle_4K_60K",
      "category": "service_proxy",
      "material": "NbTiCableProxy",
      "shape": "z_annulus_phi",
      "volume_cm3": 28.162084776795467,
      "mass_kg": 0.18305355104917054
    },
    {
      "cid": "C064",
      "name": "G10_Support_Ring_MXC_CP",
      "category": "support",
      "material": "G10",
      "shape": "z_annulus_phi",
      "volume_cm3": 15.04194562538791,
      "mass_kg": 0.027827599406967635
    },
    {
      "cid": "C065",
      "name": "G10_Support_Ring_CP_Still",
      "category": "support",
      "material": "G10",
      "shape": "z_annulus_phi",
      "volume_cm3": 16.229467648444828,
      "mass_kg": 0.03002451514962293
    },
    {
      "cid": "C066",
      "name": "G10_Support_Ring_Still_4K",
      "category": "support",
      "material": "G10",
      "shape": "z_annulus_phi",
      "volume_cm3": 36.70951015719675,
      "mass_kg": 0.067912593790814
    },
    {
      "cid": "C067",
      "name": "G10_Support_Ring_4K_60K",
      "category": "support",
      "material": "G10",
      "shape": "z_annulus_phi",
      "volume_cm3": 41.98738581522765,
      "mass_kg": 0.07767666375817114
    },
    {
      "cid": "C068",
      "name": "G10_Support_Ring_60K_Top",
      "category": "support",
      "material": "G10",
      "shape": "z_annulus_phi",
      "volume_cm3": 39.50552761889179,
      "mass_kg": 0.07308522609494982
    },
    {
      "cid": "C069",
      "name": "Passive_Cu_Liner_detector_bay",
      "category": "passive_shield",
      "material": "Copper",
      "shape": "z_annulus",
      "volume_cm3": 109.60488980809043,
      "mass_kg": 0.9820598126804904
    },
    {
      "cid": "C070",
      "name": "Passive_W_Liner_detector_bay",
      "category": "passive_shield",
      "material": "W",
      "shape": "z_annulus",
      "volume_cm3": 96.79492009936904,
      "mass_kg": 1.8681419579178224
    },
    {
      "cid": "C071",
      "name": "Passive_W_Bottom_Plate_detector_bay",
      "category": "passive_shield",
      "material": "W",
      "shape": "z_cylinder",
      "volume_cm3": 116.55585204971646,
      "mass_kg": 2.249527944559528
    },
    {
      "cid": "C072",
      "name": "W_Side_Aperture_Sleeve_collimator",
      "category": "collimator",
      "material": "W",
      "shape": "x_tube",
      "volume_cm3": 16.964600329384883,
      "mass_kg": 0.3274167863571283
    },
    {
      "cid": "C073",
      "name": "BGO_Active_Shield_Side00",
      "category": "active_shield_side",
      "material": "BGO",
      "shape": "z_annulus_phi_segment",
      "volume_cm3": 409.71271357151215,
      "mass_kg": 2.9089602663577363
    },
    {
      "cid": "C074",
      "name": "BGO_Active_Shield_Side01",
      "category": "active_shield_side",
      "material": "BGO",
      "shape": "z_annulus_phi_segment",
      "volume_cm3": 409.71271357151215,
      "mass_kg": 2.9089602663577363
    },
    {
      "cid": "C075",
      "name": "BGO_Active_Shield_Side02",
      "category": "active_shield_side",
      "material": "BGO",
      "shape": "z_annulus_phi_segment",
      "volume_cm3": 409.71271357151215,
      "mass_kg": 2.9089602663577363
    },
    {
      "cid": "C076",
      "name": "BGO_Active_Shield_Side03",
      "category": "active_shield_side",
      "material": "BGO",
      "shape": "z_annulus_phi_segment",
      "volume_cm3": 409.71271357151215,
      "mass_kg": 2.9089602663577363
    },
    {
      "cid": "C077",
      "name": "BGO_Active_Shield_Side04",
      "category": "active_shield_side",
      "material": "BGO",
      "shape": "z_annulus_phi_segment",
      "volume_cm3": 409.71271357151215,
      "mass_kg": 2.9089602663577363
    },
    {
      "cid": "C078",
      "name": "BGO_Active_Shield_Side05",
      "category": "active_shield_side",
      "material": "BGO",
      "shape": "z_annulus_phi_segment",
      "volume_cm3": 409.71271357151215,
      "mass_kg": 2.9089602663577363
    },
    {
      "cid": "C079",
      "name": "BGO_Active_Shield_Side06",
      "category": "active_shield_side",
      "material": "BGO",
      "shape": "z_annulus_phi_segment",
      "volume_cm3": 409.71271357151215,
      "mass_kg": 2.9089602663577363
    },
    {
      "cid": "C080",
      "name": "BGO_Active_Shield_Side07",
      "category": "active_shield_side",
      "material": "BGO",
      "shape": "z_annulus_phi_segment",
      "volume_cm3": 409.71271357151215,
      "mass_kg": 2.9089602663577363
    },
    {
      "cid": "C081",
      "name": "BGO_Active_Shield_Bottom00",
      "category": "active_shield_bottom",
      "material": "BGO",
      "shape": "z_annulus_phi_segment",
      "volume_cm3": 672.2567683687824,
      "mass_kg": 4.7730230554183555
    },
    {
      "cid": "C082",
      "name": "BGO_Active_Shield_Bottom01",
      "category": "active_shield_bottom",
      "material": "BGO",
      "shape": "z_annulus_phi_segment",
      "volume_cm3": 672.2567683687824,
      "mass_kg": 4.7730230554183555
    },
    {
      "cid": "C083",
      "name": "BGO_Active_Shield_Bottom02",
      "category": "active_shield_bottom",
      "material": "BGO",
      "shape": "z_annulus_phi_segment",
      "volume_cm3": 672.2567683687824,
      "mass_kg": 4.7730230554183555
    },
    {
      "cid": "C084",
      "name": "BGO_Active_Shield_Bottom03",
      "category": "active_shield_bottom",
      "material": "BGO",
      "shape": "z_annulus_phi_segment",
      "volume_cm3": 672.2567683687824,
      "mass_kg": 4.7730230554183555
    },
    {
      "cid": "C085",
      "name": "BGO_Active_Shield_Top00",
      "category": "active_shield_top",
      "material": "BGO",
      "shape": "z_annulus_phi_segment",
      "volume_cm3": 46.868816261446426,
      "mass_kg": 0.33276859545626963
    },
    {
      "cid": "C086",
      "name": "BGO_Active_Shield_Top01",
      "category": "active_shield_top",
      "material": "BGO",
      "shape": "z_annulus_phi_segment",
      "volume_cm3": 46.868816261446426,
      "mass_kg": 0.33276859545626963
    },
    {
      "cid": "C087",
      "name": "BGO_Active_Shield_Top02",
      "category": "active_shield_top",
      "material": "BGO",
      "shape": "z_annulus_phi_segment",
      "volume_cm3": 46.868816261446426,
      "mass_kg": 0.33276859545626963
    },
    {
      "cid": "C088",
      "name": "BGO_Active_Shield_Top03",
      "category": "active_shield_top",
      "material": "BGO",
      "shape": "z_annulus_phi_segment",
      "volume_cm3": 46.868816261446426,
      "mass_kg": 0.33276859545626963
    },
    {
      "cid": "C089",
      "name": "BGO_Active_Shield_Top04",
      "category": "active_shield_top",
      "material": "BGO",
      "shape": "z_annulus_phi_segment",
      "volume_cm3": 46.868816261446426,
      "mass_kg": 0.33276859545626963
    },
    {
      "cid": "C090",
      "name": "BGO_Active_Shield_Top05",
      "category": "active_shield_top",
      "material": "BGO",
      "shape": "z_annulus_phi_segment",
      "volume_cm3": 46.868816261446426,
      "mass_kg": 0.33276859545626963
    },
    {
      "cid": "C091",
      "name": "BGO_Active_Shield_Top06",
      "category": "active_shield_top",
      "material": "BGO",
      "shape": "z_annulus_phi_segment",
      "volume_cm3": 46.868816261446426,
      "mass_kg": 0.33276859545626963
    },
    {
      "cid": "C092",
      "name": "BGO_Active_Shield_Top07",
      "category": "active_shield_top",
      "material": "BGO",
      "shape": "z_annulus_phi_segment",
      "volume_cm3": 46.868816261446426,
      "mass_kg": 0.33276859545626963
    },
    {
      "cid": "C093",
      "name": "ActiveShield_Al_Backplane_detector_bay",
      "category": "shield_packaging",
      "material": "Aluminium",
      "shape": "z_annulus",
      "volume_cm3": 169.35333252223592,
      "mass_kg": 0.457253997810037
    },
    {
      "cid": "C094",
      "name": "ActiveShield_Flex_Kapton_detector_bay",
      "category": "shield_packaging",
      "material": "Kapton",
      "shape": "z_annulus",
      "volume_cm3": 51.07196699072066,
      "mass_kg": 0.07252219312682334
    },
    {
      "cid": "C095",
      "name": "Outer_Al_Mechanical_Shell_detector_bay",
      "category": "outer_shell",
      "material": "Aluminium",
      "shape": "z_shell_top_annulus",
      "volume_cm3": 1031.757910938314,
      "mass_kg": 2.7857463595334475
    }
  ],
  "total_mass_kg": 72.21487790067297,
  "source_csi_active_mass_kg": 62.83369781500205,
  "bgo_active_mass_kg": 45.02592311618547,
  "active_mass_ratio_bgo_over_csi": 0.7165887840749549,
  "bgo_density_g_cm3": 7.1
}
